{"is_source_file": true, "format": "Kotlin Script (Gradle Kotlin DSL)", "description": "This is a Gradle build script for configuring plugin management, repositories, and plugin dependencies for an Android project using Flutter.", "external_files": ["local.properties"], "external_methods": ["java.util.Properties()", "properties.load()", "file.inputStream()", "require()"], "published": [], "classes": [], "methods": [{"name": "run", "description": "Executes a block of code to determine the value of 'flutterSdkPath' based on properties loaded from 'local.properties'."}], "calls": ["java.util.Properties()", "properties.load(it)", "properties.getProperty('flutter.sdk')", "require(flutterSdkPath != null)"], "search-terms": ["settings.gradle.kts", "flutterSdkPath", "pluginManagement", "includeBuild", "repositories", "plugins", "gradlePluginPortal", "android application", "kotlin android"], "state": 2, "file_id": 15, "knowledge_revision": 33, "git_revision": "9540526c6eaa4a31c7687489efcf1339016c053a", "hash": "683f9ca2f32a701ed1517715bf394e23", "format-version": 4, "code-base-name": "flutter_frontend", "filename": "flutter_frontend/android/settings.gradle.kts", "revision_history": [{"33": "9540526c6eaa4a31c7687489efcf1339016c053a"}]}